ibroadcastdl/__init__.py
ibroadcastdl/__main__.py
ibroadcastdl/cli.py
ibroadcastdl/dl.py
ibroadcastdl/exceptions.py
ibroadcast_dl-1.1.13.dist-info/METADATA
ibroadcast_dl-1.1.13.dist-info/WHEEL
ibroadcast_dl-1.1.13.dist-info/entry_points.txt
ibroadcast_dl-1.1.13.dist-info/RECORD
