Metadata-Version: 2.3
Name: ibroadcast-dl
Version: 1.1.13
Summary: Download / Sync library from iBroadcast on Linux machines
License: Apache-2.0
Author: Marco Ceppi
Author-email: marco@ceppi.net
Requires-Python: >=3.11,<4.0
Classifier: License :: OSI Approved :: Apache Software License
Classifier: Programming Language :: Python :: 3
Classifier: Programming Language :: Python :: 3.11
Classifier: Programming Language :: Python :: 3.12
Classifier: Programming Language :: Python :: 3.13
Requires-Dist: ibroadcast (>=1.1.2,<2.0.0)
Requires-Dist: pydantic (>=2.6.1,<3.0.0)
Requires-Dist: rich (>=13.7.0,<14.0.0)
Requires-Dist: typer (>=0.9,<0.16)
